MANIFEST.in
README.md
setup.cfg
setup.py
argtest/ARGs_OAP.py
argtest/README.md
argtest/__init__.py
argtest/argoap_pipeline_stageone_version2
argtest/argoap_pipeline_stageone_version2.3
argtest/argoap_pipeline_stagetwo_version2
argtest/index.rst
argtest/stage_one.py
argtest/stage_two.py
argtest.egg-info/PKG-INFO
argtest.egg-info/SOURCES.txt
argtest.egg-info/dependency_links.txt
argtest.egg-info/entry_points.txt
argtest.egg-info/top_level.txt
argtest/DB/KO30_DIAMOND.dmnd
argtest/DB/SARG.2.2.diamondv0.9.24.dmnd
argtest/DB/SARG.2.2.fasta
argtest/DB/SARG.2.2.fasta.phr
argtest/DB/SARG.2.2.fasta.pin
argtest/DB/SARG.2.2.fasta.psq
argtest/DB/all_KO30_name.list
argtest/DB/gg85.fasta
argtest/DB/gg85_yinxiaole.fasta.mmi
argtest/DB/structure_20181107.LIST
argtest/DB/update_45_sarg2.0_16s.table_201704.txt
argtest/DB/update_45_sarg2.0_cell.table_201704.txt
argtest/bin/Fq2fa.pl
argtest/bin/blastx
argtest/bin/copy_correction.pl
argtest/bin/de-replicate.pl
argtest/bin/diamond
argtest/bin/diamondv0.9.24
argtest/bin/divide_extract.fa_meta_data_online.pl
argtest/bin/extract_usearch_reads.pl
argtest/bin/fastp
argtest/bin/merge_extracted_fa_update_metadate.v2.3.pl
argtest/bin/minimap2
argtest/bin/obtain_community.pl
argtest/bin/samtools
argtest/bin/bbmap/README.md
argtest/bin/bbmap/a_sample_mt.sh
argtest/bin/bbmap/addadapters.sh
argtest/bin/bbmap/addssu.sh
argtest/bin/bbmap/adjusthomopolymers.sh
argtest/bin/bbmap/alltoall.sh
argtest/bin/bbmap/analyzeaccession.sh
argtest/bin/bbmap/analyzegenes.sh
argtest/bin/bbmap/analyzesketchresults.sh
argtest/bin/bbmap/applyvariants.sh
argtest/bin/bbmap/bbcms.sh
argtest/bin/bbmap/bbcountunique.sh
argtest/bin/bbmap/bbduk.sh
argtest/bin/bbmap/bbest.sh
argtest/bin/bbmap/bbfakereads.sh
argtest/bin/bbmap/bbmap.sh
argtest/bin/bbmap/bbmapskimmer.sh
argtest/bin/bbmap/bbmask.sh
argtest/bin/bbmap/bbmerge-auto.sh
argtest/bin/bbmap/bbmerge.sh
argtest/bin/bbmap/bbnorm.sh
argtest/bin/bbmap/bbrealign.sh
argtest/bin/bbmap/bbrename.sh
argtest/bin/bbmap/bbsketch.sh
argtest/bin/bbmap/bbsplit.sh
argtest/bin/bbmap/bbsplitpairs.sh
argtest/bin/bbmap/bbstats.sh
argtest/bin/bbmap/bbversion.sh
argtest/bin/bbmap/bbwrap.sh
